txzpkg/__init__.py
txzpkg/download.py
txzpkg-0.0.6.dist-info/LICENSE
txzpkg-0.0.6.dist-info/METADATA
txzpkg-0.0.6.dist-info/WHEEL
txzpkg-0.0.6.dist-info/top_level.txt
txzpkg-0.0.6.dist-info/RECORD
